h5preserve/__init__.py
h5preserve/_utils.py
h5preserve/_version.py
h5preserve/additional_registries.py
h5preserve-0.19.0.dist-info/LICENSE.txt
h5preserve-0.19.0.dist-info/METADATA
h5preserve-0.19.0.dist-info/WHEEL
h5preserve-0.19.0.dist-info/top_level.txt
h5preserve-0.19.0.dist-info/RECORD
