Metadata-Version: 2.1
Name: h5preserve
Version: 0.19.0
Summary: Thin wrapper around h5py, inspired by camel
Home-page: https://h5preserve.readthedocs.io
Author: James Tocknell
Author-email: aragilar@gmail.com
License: 3-clause BSD
Project-URL: Documentation, https://h5preserve.readthedocs.io
Project-URL: Source, https://github.com/h5preserve/h5preserve/
Project-URL: Tracker, https://github.com/h5preserve/h5preserve/issues
Keywords: hdf5
Platform: UNKNOWN
Classifier: Development Status :: 3 - Alpha
Classifier: Intended Audience :: Developers
Classifier: Intended Audience :: Science/Research
Classifier: License :: OSI Approved :: BSD License
Classifier: Topic :: Scientific/Engineering
Classifier: Programming Language :: Python :: 3
Classifier: Programming Language :: Python :: 3.7
Classifier: Programming Language :: Python :: 3.8
Classifier: Programming Language :: Python :: 3.9
Classifier: Programming Language :: Python :: 3.10
Classifier: Programming Language :: Python :: 3.11
Classifier: Programming Language :: Python :: 3.12
Classifier: Programming Language :: Python :: 3 :: Only
Requires-Python: >=3.5
License-File: LICENSE.txt
Requires-Dist: h5py
